streaminghub_rpc_websocket/__init__.py
streaminghub_rpc_websocket/client.py
streaminghub_rpc_websocket/server.py
streaminghub_rpc_websocket-0.0.1.dist-info/METADATA
streaminghub_rpc_websocket-0.0.1.dist-info/WHEEL
streaminghub_rpc_websocket-0.0.1.dist-info/entry_points.txt
streaminghub_rpc_websocket-0.0.1.dist-info/top_level.txt
streaminghub_rpc_websocket-0.0.1.dist-info/RECORD
